{
  "data": {
    "address": "3T9mBXQzfAn8Rf1LKDutvGMTd1EruJbFh3cM7MSMq3Py",
    "decimals": 6,
    "symbol": "CHIPPY",
    "name": "CHIPPY",
    "extensions": {
      "coingeckoId": "chippy",
      "description": "Hey, my name is Chippy. I’m a degenerate bong smoking, hoe pimping, lambo driving chipmunk that loves to munch on nuts. Let me taste your nutz fam.",
      "telegram": "https://t.me/chippysolana",
      "twitter": "https://twitter.com/Chippy_Solana",
      "website": "https://chippyonsolana.com/"
    },
    "logoURI": "https://imgur.fotofolio.xyz/?url=https%3A%2F%2Fi.imgur.com%2FgZihYiE.png",
    "numberMarkers": 1,
    "liquidity": 57890.92868771376,
    "lastTradeUnixTime": 1724480262,
    "lastTradeHumanTime": "2024-08-24T06:17:42",
    "price": 0.0001508080117563919,
    "history30mPrice": 0.0001508080117563919,
    "priceChange30mPercent": 0,
    "history1hPrice": 0.0001508080117563919,
    "priceChange1hPercent": 0,
    "history2hPrice": 0.0001508080117563919,
    "priceChange2hPercent": 0,
    "history4hPrice": 0.0001501269027719044,
    "priceChange4hPercent": 0.4536888271933097,
    "history6hPrice": 0.0001510544634144087,
    "priceChange6hPercent": -0.1631541713141477,
    "history8hPrice": 0.00015594257294747875,
    "priceChange8hPercent": -3.2925974568959875,
    "history12hPrice": 0.00015226317574094646,
    "priceChange12hPercent": -0.9556900264777833,
    "history24hPrice": 0.00014485209169765842,
    "priceChange24hPercent": 4.111725270191421,
    "uniqueWallet30m": 0,
    "uniqueWalletHistory30m": 0,
    "uniqueWallet30mChangePercent": 0,
    "uniqueWallet1h": 0,
    "uniqueWalletHistory1h": 0,
    "uniqueWallet1hChangePercent": 0,
    "uniqueWallet2h": 0,
    "uniqueWalletHistory2h": 4,
    "uniqueWallet2hChangePercent": -100,
    "uniqueWallet4h": 5,
    "uniqueWalletHistory4h": 3,
    "uniqueWallet4hChangePercent": 66.66666666666666,
    "uniqueWallet8h": 8,
    "uniqueWalletHistory8h": 15,
    "uniqueWallet8hChangePercent": -46.666666666666664,
    "uniqueWallet24h": 32,
    "uniqueWalletHistory24h": 32,
    "uniqueWallet24hChangePercent": 0,
    "supply": 999922995.504974,
    "mc": 150796.39886160073,
    "holder": 3252,
    "trade30m": 0,
    "tradeHistory30m": 0,
    "trade30mChangePercent": 0,
    "sell30m": 0,
    "sellHistory30m": 0,
    "sell30mChangePercent": 0,
    "buy30m": 0,
    "buyHistory30m": 0,
    "buy30mChangePercent": 0,
    "v30m": 0,
    "v30mUSD": 0,
    "vHistory30m": 0,
    "vHistory30mUSD": 0,
    "v30mChangePercent": 0,
    "vBuy30m": 0,
    "vBuy30mUSD": 0,
    "vBuyHistory30m": 0,
    "vBuyHistory30mUSD": 0,
    "vBuy30mChangePercent": 0,
    "vSell30m": 0,
    "vSell30mUSD": 0,
    "vSellHistory30m": 0,
    "vSellHistory30mUSD": 0,
    "vSell30mChangePercent": 0,
    "trade1h": 0,
    "tradeHistory1h": 0,
    "trade1hChangePercent": 0,
    "sell1h": 0,
    "sellHistory1h": 0,
    "sell1hChangePercent": 0,
    "buy1h": 0,
    "buyHistory1h": 0,
    "buy1hChangePercent": 0,
    "v1h": 0,
    "v1hUSD": 0,
    "vHistory1h": 0,
    "vHistory1hUSD": 0,
    "v1hChangePercent": 0,
    "vBuy1h": 0,
    "vBuy1hUSD": 0,
    "vBuyHistory1h": 0,
    "vBuyHistory1hUSD": 0,
    "vBuy1hChangePercent": 0,
    "vSell1h": 0,
    "vSell1hUSD": 0,
    "vSellHistory1h": 0,
    "vSellHistory1hUSD": 0,
    "vSell1hChangePercent": 0,
    "trade2h": 0,
    "tradeHistory2h": 4,
    "trade2hChangePercent": -100,
    "sell2h": 0,
    "sellHistory2h": 2,
    "sell2hChangePercent": -100,
    "buy2h": 0,
    "buyHistory2h": 2,
    "buy2hChangePercent": -100,
    "v2h": 0,
    "v2hUSD": 0,
    "vHistory2h": 2015677.630839982,
    "vHistory2hUSD": 305.90789860796815,
    "v2hChangePercent": -100,
    "vBuy2h": 0,
    "vBuy2hUSD": 0,
    "vBuyHistory2h": 854830.1744350345,
    "vBuyHistory2hUSD": 130.06883899664294,
    "vBuy2hChangePercent": 0,
    "vSell2h": 0,
    "vSell2hUSD": 0,
    "vSellHistory2h": 1160847.4564049477,
    "vSellHistory2hUSD": 175.8390596113252,
    "vSell2hChangePercent": 0,
    "trade4h": 4,
    "tradeHistory4h": 4,
    "trade4hChangePercent": 0,
    "sell4h": 2,
    "sellHistory4h": 4,
    "sell4hChangePercent": -50,
    "buy4h": 2,
    "buyHistory4h": 0,
    "buy4hChangePercent": 0,
    "v4h": 2015677.6308399602,
    "v4hUSD": 305.9078986078593,
    "vHistory4h": 3270924.3188050804,
    "vHistory4hUSD": 496.4265335994496,
    "v4hChangePercent": -38.37590129335922,
    "vBuy4h": 854830.17443494,
    "vBuy4hUSD": 130.06883899664726,
    "vBuyHistory4h": 5.999027052894235e-8,
    "vBuyHistory4hUSD": 2.255529096828468e-11,
    "vBuy4hChangePercent": 1424948023900753.5,
    "vSell4h": 1160847.4564050203,
    "vSell4hUSD": 175.83905961121204,
    "vSellHistory4h": 3270924.3188050203,
    "vSellHistory4hUSD": 496.42653359942705,
    "vSell4hChangePercent": -64.51010958183474,
    "trade8h": 8,
    "tradeHistory8h": 14,
    "trade8hChangePercent": -42.857142857142854,
    "sell8h": 6,
    "sellHistory8h": 6,
    "sell8hChangePercent": 0,
    "buy8h": 2,
    "buyHistory8h": 8,
    "buy8hChangePercent": -75,
    "v8h": 5286601.949645268,
    "v8hUSD": 802.3344322071625,
    "vHistory8h": 8598099.595232362,
    "vHistory8hUSD": 1215.6463717120907,
    "v8hChangePercent": -38.51429736198121,
    "vBuy8h": 854830.1744350967,
    "vBuy8hUSD": 130.0688389964319,
    "vBuyHistory8h": 6334514.011700147,
    "vBuyHistory8hUSD": 875.7832092784132,
    "vBuy8hChangePercent": -86.5051971965618,
    "vSell8h": 4431771.775210171,
    "vSell8hUSD": 672.2655932107307,
    "vSellHistory8h": 2263585.583532215,
    "vSellHistory8hUSD": 339.86316243367753,
    "vSell8hChangePercent": 95.78547449019386,
    "trade24h": 43,
    "tradeHistory24h": 59,
    "trade24hChangePercent": -27.11864406779661,
    "sell24h": 26,
    "sellHistory24h": 24,
    "sell24hChangePercent": 8.333333333333332,
    "buy24h": 17,
    "buyHistory24h": 35,
    "buy24hChangePercent": -51.42857142857142,
    "v24h": 23972123.706772044,
    "v24hUSD": 3486.2767801077034,
    "vHistory24h": 50460616.56826833,
    "vHistory24hUSD": 6611.224312833867,
    "v24hChangePercent": -52.49339913566041,
    "vBuy24h": 11115665.41856376,
    "vBuy24hUSD": 1612.2574635482954,
    "vBuyHistory24h": 32544030.964724857,
    "vBuyHistory24hUSD": 4356.662428944836,
    "vBuy24hChangePercent": -65.84422676277484,
    "vSell24h": 12856458.288208283,
    "vSell24hUSD": 1874.019316559408,
    "vSellHistory24h": 17916585.603543468,
    "vSellHistory24hUSD": 2254.5618838890305,
    "vSell24hChangePercent": -28.242698845110386,
    "watch": 12,
    "view30m": 0,
    "viewHistory30m": 0,
    "view30mChangePercent": 0,
    "view1h": 0,
    "viewHistory1h": 0,
    "view1hChangePercent": 0,
    "view2h": 0,
    "viewHistory2h": 3,
    "view2hChangePercent": -100,
    "view4h": 3,
    "viewHistory4h": 1,
    "view4hChangePercent": 200,
    "view8h": 4,
    "viewHistory8h": 8,
    "view8hChangePercent": -50,
    "view24h": 19,
    "viewHistory24h": 2,
    "view24hChangePercent": 850,
    "uniqueView30m": 0,
    "uniqueViewHistory30m": 0,
    "uniqueView30mChangePercent": 0,
    "uniqueView1h": 0,
    "uniqueViewHistory1h": 0,
    "uniqueView1hChangePercent": 0,
    "uniqueView2h": 0,
    "uniqueViewHistory2h": 1,
    "uniqueView2hChangePercent": -100,
    "uniqueView4h": 1,
    "uniqueViewHistory4h": 2,
    "uniqueView4hChangePercent": -50,
    "uniqueView8h": 2,
    "uniqueViewHistory8h": 5,
    "uniqueView8hChangePercent": -60,
    "uniqueView24h": 7,
    "uniqueViewHistory24h": 2,
    "uniqueView24hChangePercent": 250
  },
  "success": true,
  "statusCode": 200
}
