{
  "data": {
    "address": "7rx8j3xEbQSrJUdrp3x3VxUT6qGPM1KQR6d4UuW8tdwU",
    "decimals": 9,
    "symbol": "Cheers",
    "name": "DiCaprio",
    "extensions": {
      "description": "CHEERS"
    },
    "logoURI": "https://img.fotofolio.xyz/?w=30\u0026h=30\u0026url=https%3A%2F%2Fbafkreiefeq6hhcrtsicn65ognmenccfy4jl4j6q33b6hju3s55r4bnvijy.ipfs.nftstorage.link",
    "numberMarkers": 1,
    "liquidity": 97098.6957361859,
    "lastTradeUnixTime": 1724882629,
    "lastTradeHumanTime": "2024-08-28T22:03:49",
    "price": 0.000471301484301884,
    "history30mPrice": 0.0004811104020076119,
    "priceChange30mPercent": -2.038808070828765,
    "history1hPrice": 0.0004821449664921286,
    "priceChange1hPercent": -2.249008689054031,
    "history2hPrice": 0.0004960436992729659,
    "priceChange2hPercent": -4.987910340832001,
    "history4hPrice": 0.00044668957389450283,
    "priceChange4hPercent": 5.509846624088411,
    "history6hPrice": 0.0004606438819940994,
    "priceChange6hPercent": 2.3136315762294504,
    "history8hPrice": 0.0004606438819940994,
    "priceChange8hPercent": 2.3136315762294504,
    "history12hPrice": 0.0004627610283403795,
    "priceChange12hPercent": 1.8455434745949855,
    "history24hPrice": 0.00045546193074614286,
    "priceChange24hPercent": 3.477689898207872,
    "uniqueWallet30m": 3,
    "uniqueWalletHistory30m": 1,
    "uniqueWallet30mChangePercent": 200,
    "uniqueWallet1h": 3,
    "uniqueWalletHistory1h": 12,
    "uniqueWallet1hChangePercent": -75,
    "uniqueWallet2h": 8,
    "uniqueWalletHistory2h": 19,
    "uniqueWallet2hChangePercent": -57.89473684210527,
    "uniqueWallet4h": 24,
    "uniqueWalletHistory4h": 1,
    "uniqueWallet4hChangePercent": 2300,
    "uniqueWallet8h": 24,
    "uniqueWalletHistory8h": 11,
    "uniqueWallet8hChangePercent": 118.18181818181819,
    "uniqueWallet24h": 42,
    "uniqueWalletHistory24h": 19,
    "uniqueWallet24hChangePercent": 121.05263157894737,
    "supply": 999955430.3555802,
    "mc": 471280.4785623141,
    "holder": 5543,
    "trade30m": 2,
    "tradeHistory30m": 1,
    "trade30mChangePercent": 100,
    "sell30m": 2,
    "sellHistory30m": 1,
    "sell30mChangePercent": 100,
    "buy30m": 0,
    "buyHistory30m": 0,
    "buy30mChangePercent": 0,
    "v30m": 180000.00000000437,
    "v30mUSD": 85.49948035333088,
    "vHistory30m": 516350.86000000435,
    "vHistory30mUSD": 248.42176983157825,
    "v30mChangePercent": -65.1399825304827,
    "vBuy30m": 3.41970007866621e-9,
    "vBuy30mUSD": 9.734435479913373e-13,
    "vBuyHistory30m": 3.41970007866621e-9,
    "vBuyHistory30mUSD": 9.734435479913373e-13,
    "vBuy30mChangePercent": 0,
    "vSell30m": 180000.00000000093,
    "vSell30mUSD": 85.49948035332991,
    "vSellHistory30m": 516350.8600000009,
    "vSellHistory30mUSD": 248.42176983157728,
    "vSell30mChangePercent": -65.13998253048314,
    "trade1h": 3,
    "tradeHistory1h": 2,
    "trade1hChangePercent": 50,
    "sell1h": 3,
    "sellHistory1h": 2,
    "sell1hChangePercent": 50,
    "buy1h": 0,
    "buyHistory1h": 0,
    "buy1hChangePercent": 0,
    "v1h": 696350.8599999985,
    "v1hUSD": 333.9212501849053,
    "vHistory1h": 1199999.9999999977,
    "vHistory1hUSD": 584.1240195994926,
    "v1hChangePercent": -41.97076166666668,
    "vBuy1h": 1.5570549294352531e-9,
    "vBuy1hUSD": 5.186961971048731e-13,
    "vBuyHistory1h": 1.5570549294352531e-9,
    "vBuyHistory1hUSD": 5.186961971048731e-13,
    "vBuy1hChangePercent": 0,
    "vSell1h": 696350.859999997,
    "vSell1hUSD": 333.9212501849048,
    "vSellHistory1h": 1199999.999999996,
    "vSellHistory1hUSD": 584.124019599492,
    "vSell1hChangePercent": -41.970761666666725,
    "trade2h": 5,
    "tradeHistory2h": 34,
    "trade2hChangePercent": -85.29411764705883,
    "sell2h": 5,
    "sellHistory2h": 13,
    "sell2hChangePercent": -61.53846153846154,
    "buy2h": 0,
    "buyHistory2h": 21,
    "buy2hChangePercent": -100,
    "v2h": 1896350.8599999943,
    "v2hUSD": 918.0452697843994,
    "vHistory2h": 20263809.937795818,
    "vHistory2hUSD": 10003.953136363107,
    "v2hChangePercent": -90.64168650504885,
    "vBuy2h": 1.5570549294352531e-9,
    "vBuy2hUSD": 1.4281908988778014e-12,
    "vBuyHistory2h": 12373666.287799438,
    "vBuyHistory2hUSD": 6086.341725839928,
    "vBuy2hChangePercent": -99.99999999999999,
    "vSell2h": 1896350.8599999927,
    "vSell2hUSD": 918.0452697843979,
    "vSellHistory2h": 7890143.649996379,
    "vSellHistory2hUSD": 3917.61141052318,
    "vSell2hChangePercent": -75.96557243921835,
    "trade4h": 39,
    "tradeHistory4h": 1,
    "trade4hChangePercent": 3800,
    "sell4h": 18,
    "sellHistory4h": 0,
    "sell4hChangePercent": 0,
    "buy4h": 21,
    "buyHistory4h": 1,
    "buy4hChangePercent": 2000,
    "v4h": 22160160.79779578,
    "v4hUSD": 10921.998406147504,
    "vHistory4h": 426108.64999997325,
    "vHistory4hUSD": 190.3382913012632,
    "v4hChangePercent": 5100.589285807076,
    "vBuy4h": 12373666.287799397,
    "vBuy4hUSD": 6086.3417258399295,
    "vBuyHistory4h": 426108.6499999652,
    "vBuyHistory4hUSD": 190.3382913012622,
    "vBuy4hChangePercent": 2803.8758748033883,
    "vSell4h": 9786494.50999638,
    "vSell4hUSD": 4835.656680307574,
    "vSellHistory4h": 8.032657206058502e-9,
    "vSellHistory4hUSD": 1.0231815394945443e-12,
    "vSell4hChangePercent": 121833837283820200,
    "trade8h": 40,
    "tradeHistory8h": 12,
    "trade8hChangePercent": 233.33333333333334,
    "sell8h": 18,
    "sellHistory8h": 5,
    "sell8hChangePercent": 260,
    "buy8h": 22,
    "buyHistory8h": 7,
    "buy8hChangePercent": 214.28571428571428,
    "v8h": 22586269.447795838,
    "v8hUSD": 11112.336697448758,
    "vHistory8h": 3258644.9848570097,
    "vHistory8hUSD": 1506.9146268960017,
    "v8hChangePercent": 593.118445021004,
    "vBuy8h": 12799774.937799444,
    "vBuy8hUSD": 6276.680017141195,
    "vBuyHistory8h": 1475238.6938328822,
    "vBuyHistory8hUSD": 683.7760538612775,
    "vBuy8hChangePercent": 767.6409445676746,
    "vSell8h": 9786494.509996394,
    "vSell8hUSD": 4835.656680307564,
    "vSellHistory8h": 1783406.2910241275,
    "vSellHistory8hUSD": 823.1385730347241,
    "vSell8hChangePercent": 448.7529431320142,
    "trade24h": 71,
    "tradeHistory24h": 31,
    "trade24hChangePercent": 129.03225806451613,
    "sell24h": 30,
    "sellHistory24h": 9,
    "sell24hChangePercent": 233.33333333333334,
    "buy24h": 41,
    "buyHistory24h": 22,
    "buy24hChangePercent": 86.36363636363636,
    "v24h": 27916961.340591855,
    "v24hUSD": 13565.86980416617,
    "vHistory24h": 1481811.9906141153,
    "vHistory24hUSD": 705.3659699637994,
    "v24hChangePercent": 1783.9745876953039,
    "vBuy24h": 16022471.853744667,
    "vBuy24hUSD": 7760.594368144264,
    "vBuyHistory24h": 635584.2160377895,
    "vBuyHistory24hUSD": 308.04441356970995,
    "vBuy24hChangePercent": 2420.9046180580467,
    "vSell24h": 11894489.486847186,
    "vSell24hUSD": 5805.275436021905,
    "vSellHistory24h": 846227.7745763257,
    "vSellHistory24hUSD": 397.3215563940895,
    "vSell24hChangePercent": 1305.589587602736,
    "watch": 5,
    "view30m": 0,
    "viewHistory30m": 0,
    "view30mChangePercent": 0,
    "view1h": 0,
    "viewHistory1h": 1,
    "view1hChangePercent": -100,
    "view2h": 1,
    "viewHistory2h": 4,
    "view2hChangePercent": -75,
    "view4h": 5,
    "viewHistory4h": 0,
    "view4hChangePercent": 0,
    "view8h": 5,
    "viewHistory8h": 1,
    "view8hChangePercent": 400,
    "view24h": 6,
    "viewHistory24h": 1,
    "view24hChangePercent": 500,
    "uniqueView30m": 0,
    "uniqueViewHistory30m": 0,
    "uniqueView30mChangePercent": 0,
    "uniqueView1h": 0,
    "uniqueViewHistory1h": 3,
    "uniqueView1hChangePercent": -100,
    "uniqueView2h": 5,
    "uniqueViewHistory2h": 4,
    "uniqueView2hChangePercent": 25,
    "uniqueView4h": 5,
    "uniqueViewHistory4h": 1,
    "uniqueView4hChangePercent": 400,
    "uniqueView8h": 5,
    "uniqueViewHistory8h": 1,
    "uniqueView8hChangePercent": 400,
    "uniqueView24h": 6,
    "uniqueViewHistory24h": 1,
    "uniqueView24hChangePercent": 500
  },
  "success": true,
  "statusCode": 200
}
