{
  "data": {
    "address": "AHW5N8iqZobTcBepkSJzZ61XtAuSzBDcpxtrLG6KUKPk",
    "decimals": 9,
    "symbol": "BENDOG",
    "name": "Ben the Dog",
    "extensions": {
      "coingeckoId": "ben-the-dog",
      "description": "$BENDOG, a project created by one of Solana’s earliest advisors and Anatoly’s most trusted source of guidance, Talking Ben The Dog.",
      "telegram": "https://t.me/ben_talking",
      "twitter": "https://twitter.com/ben_dog_",
      "website": "https://benthedog.io"
    },
    "logoURI": "https://img.fotofolio.xyz/?w=30\u0026h=30\u0026url=https%3A%2F%2Fbafkreic26nzla2vtal5pmkzoegrt7nherbu64ro42n2bmgoriivytwa7r4.ipfs.nftstorage.link",
    "numberMarkers": 4,
    "liquidity": 564759.6226491939,
    "lastTradeUnixTime": 1724883464,
    "lastTradeHumanTime": "2024-08-28T22:17:44",
    "price": 0.01012739951974126,
    "history30mPrice": 0.010279405397393183,
    "priceChange30mPercent": -1.1710444986686412,
    "history1hPrice": 0.010312979984307635,
    "priceChange1hPercent": -1.4927886852367276,
    "history2hPrice": 0.010317521886017596,
    "priceChange2hPercent": -1.5361527872426841,
    "history4hPrice": 0.010122203956337835,
    "priceChange4hPercent": 0.3638044620734014,
    "history6hPrice": 0.01032199405420721,
    "priceChange6hPercent": -1.5788138160147718,
    "history8hPrice": 0.011151548816935882,
    "priceChange8hPercent": -8.900286832241436,
    "history12hPrice": 0.011122367516399681,
    "priceChange12hPercent": -8.66127224251579,
    "history24hPrice": 0.010203485271856275,
    "priceChange24hPercent": -0.4356970650776968,
    "uniqueWallet30m": 19,
    "uniqueWalletHistory30m": 20,
    "uniqueWallet30mChangePercent": -5,
    "uniqueWallet1h": 26,
    "uniqueWalletHistory1h": 26,
    "uniqueWallet1hChangePercent": 0,
    "uniqueWallet2h": 32,
    "uniqueWalletHistory2h": 40,
    "uniqueWallet2hChangePercent": -20,
    "uniqueWallet4h": 47,
    "uniqueWalletHistory4h": 56,
    "uniqueWallet4hChangePercent": -16.071428571428573,
    "uniqueWallet8h": 74,
    "uniqueWalletHistory8h": 70,
    "uniqueWallet8hChangePercent": 5.714285714285714,
    "uniqueWallet24h": 151,
    "uniqueWalletHistory24h": 154,
    "uniqueWallet24hChangePercent": -1.948051948051948,
    "supply": 999977554.9308085,
    "mc": 10127172.20955831,
    "holder": 13404,
    "trade30m": 28,
    "tradeHistory30m": 27,
    "trade30mChangePercent": 3.7037037037037033,
    "sell30m": 15,
    "sellHistory30m": 13,
    "sell30mChangePercent": 15.384615384615385,
    "buy30m": 13,
    "buyHistory30m": 14,
    "buy30mChangePercent": -7.142857142857142,
    "v30m": 391667.0149677829,
    "v30mUSD": 4008.0786425950046,
    "vHistory30m": 384239.6060681271,
    "vHistory30mUSD": 3969.8278811858213,
    "v30mChangePercent": 1.9330149163069077,
    "vBuy30m": 163455.49933790532,
    "vBuy30mUSD": 1674.67274259432,
    "vBuyHistory30m": 186764.88216821765,
    "vBuyHistory30mUSD": 1934.8632052871494,
    "vBuy30mChangePercent": -12.480602648477433,
    "vSell30m": 228211.51562987757,
    "vSell30mUSD": 2333.4059000006846,
    "vSellHistory30m": 197474.72389990947,
    "vSellHistory30mUSD": 2034.9646758986719,
    "vSell30mChangePercent": 15.564924524491103,
    "trade1h": 55,
    "tradeHistory1h": 103,
    "trade1hChangePercent": -46.601941747572816,
    "sell1h": 28,
    "sellHistory1h": 51,
    "sell1hChangePercent": -45.09803921568628,
    "buy1h": 27,
    "buyHistory1h": 52,
    "buy1hChangePercent": -48.07692307692308,
    "v1h": 775906.6210358869,
    "v1hUSD": 7977.906523781048,
    "vHistory1h": 1432357.9907100918,
    "vHistory1hUSD": 14903.988343226769,
    "v1hChangePercent": -45.8301188621686,
    "vBuy1h": 350220.3815060957,
    "vBuy1hUSD": 3609.535947882117,
    "vBuyHistory1h": 745184.1985518684,
    "vBuyHistory1hUSD": 7780.024862597652,
    "vBuy1hChangePercent": -53.00217286052414,
    "vSell1h": 425686.2395297913,
    "vSell1hUSD": 4368.370575898932,
    "vSellHistory1h": 687173.7921582235,
    "vSellHistory1hUSD": 7123.963480629117,
    "vSell1hChangePercent": -38.05260846854648,
    "trade2h": 158,
    "tradeHistory2h": 251,
    "trade2hChangePercent": -37.05179282868526,
    "sell2h": 79,
    "sellHistory2h": 118,
    "sell2hChangePercent": -33.05084745762712,
    "buy2h": 79,
    "buyHistory2h": 133,
    "buy2hChangePercent": -40.6015037593985,
    "v2h": 2208264.611745948,
    "v2hUSD": 22881.89486700659,
    "vHistory2h": 2735703.6094463696,
    "vHistory2hUSD": 28295.76492024349,
    "v2hChangePercent": -19.279829725675604,
    "vBuy2h": 1095404.5800579693,
    "vBuy2hUSD": 11389.560810479992,
    "vBuyHistory2h": 1398509.9945033698,
    "vBuyHistory2hUSD": 14489.741249528302,
    "vBuy2hChangePercent": -21.673453578216105,
    "vSell2h": 1112860.031687979,
    "vSell2hUSD": 11492.334056526599,
    "vSellHistory2h": 1337193.6149429998,
    "vSellHistory2hUSD": 13806.023670715187,
    "vSell2hChangePercent": -16.776447385637834,
    "trade4h": 409,
    "tradeHistory4h": 591,
    "trade4hChangePercent": -30.79526226734349,
    "sell4h": 197,
    "sellHistory4h": 328,
    "sell4hChangePercent": -39.9390243902439,
    "buy4h": 212,
    "buyHistory4h": 263,
    "buy4hChangePercent": -19.39163498098859,
    "v4h": 4943968.221192405,
    "v4hUSD": 51177.659787250974,
    "vHistory4h": 7649677.177070235,
    "vHistory4hUSD": 80266.50016246826,
    "v4hChangePercent": -35.37023711259532,
    "vBuy4h": 2493914.5745613524,
    "vBuy4hUSD": 25879.302060008904,
    "vBuyHistory4h": 3374043.790111975,
    "vBuyHistory4hUSD": 35497.82173442405,
    "vBuy4hChangePercent": -26.085293206031967,
    "vSell4h": 2450053.6466310523,
    "vSell4hUSD": 25298.35772724207,
    "vSellHistory4h": 4275633.38695826,
    "vSellHistory4hUSD": 44768.678428044215,
    "vSell4hChangePercent": -42.69729359621145,
    "trade8h": 1000,
    "tradeHistory8h": 710,
    "trade8hChangePercent": 40.845070422535215,
    "sell8h": 525,
    "sellHistory8h": 310,
    "sell8hChangePercent": 69.35483870967742,
    "buy8h": 475,
    "buyHistory8h": 400,
    "buy8hChangePercent": 18.75,
    "v8h": 12593645.398262452,
    "v8hUSD": 131444.1599497145,
    "vHistory8h": 9550564.840303948,
    "vHistory8hUSD": 105832.96557407836,
    "v8hChangePercent": 31.862833338574113,
    "vBuy8h": 5867958.364673366,
    "vBuy8hUSD": 61377.12379442747,
    "vBuyHistory8h": 5058645.559254969,
    "vBuyHistory8hUSD": 56121.680873625606,
    "vBuy8hChangePercent": 15.998606661376607,
    "vSell8h": 6725687.033589086,
    "vSell8hUSD": 70067.03615528702,
    "vSellHistory8h": 4491919.28104898,
    "vSellHistory8hUSD": 49711.28470045276,
    "vSell8hChangePercent": 49.72858176602104,
    "trade24h": 2442,
    "tradeHistory24h": 2145,
    "trade24hChangePercent": 13.846153846153847,
    "sell24h": 1197,
    "sellHistory24h": 1024,
    "sell24hChangePercent": 16.89453125,
    "buy24h": 1245,
    "buyHistory24h": 1121,
    "buy24hChangePercent": 11.061552185548617,
    "v24h": 30823030.472366467,
    "v24hUSD": 329332.1464150529,
    "vHistory24h": 27891936.41625604,
    "vHistory24hUSD": 327407.40873849206,
    "v24hChangePercent": 10.508750673912049,
    "vBuy24h": 15514192.953258157,
    "vBuy24hUSD": 166262.6652165548,
    "vBuyHistory24h": 13296905.411666274,
    "vBuyHistory24hUSD": 156968.3807957973,
    "vBuy24hChangePercent": 16.675214818378016,
    "vSell24h": 15308837.519108308,
    "vSell24hUSD": 163069.48119849808,
    "vSellHistory24h": 14595031.004589766,
    "vSellHistory24hUSD": 170439.02794269472,
    "vSell24hChangePercent": 4.8907502443404764,
    "watch": 43,
    "view30m": 0,
    "viewHistory30m": 0,
    "view30mChangePercent": 0,
    "view1h": 0,
    "viewHistory1h": 0,
    "view1hChangePercent": 0,
    "view2h": 0,
    "viewHistory2h": 2,
    "view2hChangePercent": -100,
    "view4h": 2,
    "viewHistory4h": 3,
    "view4hChangePercent": -33.33333333333333,
    "view8h": 5,
    "viewHistory8h": 6,
    "view8hChangePercent": -16.666666666666664,
    "view24h": 15,
    "viewHistory24h": 21,
    "view24hChangePercent": -28.57142857142857,
    "uniqueView30m": 0,
    "uniqueViewHistory30m": 0,
    "uniqueView30mChangePercent": 0,
    "uniqueView1h": 0,
    "uniqueViewHistory1h": 0,
    "uniqueView1hChangePercent": 0,
    "uniqueView2h": 0,
    "uniqueViewHistory2h": 3,
    "uniqueView2hChangePercent": -100,
    "uniqueView4h": 4,
    "uniqueViewHistory4h": 2,
    "uniqueView4hChangePercent": 100,
    "uniqueView8h": 4,
    "uniqueViewHistory8h": 8,
    "uniqueView8hChangePercent": -50,
    "uniqueView24h": 11,
    "uniqueViewHistory24h": 23,
    "uniqueView24hChangePercent": -52.17391304347826
  },
  "success": true,
  "statusCode": 200
}
