{
  "data": {
    "address": "PUPS8ZgJ5po4UmNDfqtDMCPP6M1KP3EEzG9Zufcwzrg",
    "decimals": 9,
    "symbol": "PUPS",
    "name": "PUPS",
    "extensions": {
      "coingeckoId": "pups-ordinals",
      "description": "$PUPS, the first meme coin on Bitcoin, and has forever changed the cryptocurrency landscape by conducting the first-ever successful BRC-20 token airdrop on Bitcoin. This milestone is more than a historical feat; it's a testament to $PUPS being 100% free and fair launch. PUPS is just a meme coin. There is zero utility ever. No roadmap. No promises. Only community run memes.",
      "twitter": "https://twitter.com/PupsToken",
      "website": "https://www.pupstoken.com/"
    },
    "logoURI": "https://img.fotofolio.xyz/?url=https%3A%2F%2Ftoken-ndllmwrhm.pages.dev%2Fpups%2Ficon.png",
    "numberMarkers": 12,
    "liquidity": 441925.2607590965,
    "lastTradeUnixTime": 1724489514,
    "lastTradeHumanTime": "2024-08-24T08:51:54",
    "price": 4.620342495176227,
    "history30mPrice": 4.592839189683911,
    "priceChange30mPercent": 0.5924639712137098,
    "history1hPrice": 4.418129039708529,
    "priceChange1hPercent": 4.5702845167094415,
    "history2hPrice": 4.379454327212776,
    "priceChange2hPercent": 5.493738761717345,
    "history4hPrice": 4.299242342689335,
    "priceChange4hPercent": 7.461960477635218,
    "history6hPrice": 4.2296255908861715,
    "priceChange6hPercent": 9.230711037252835,
    "history8hPrice": 4.292687177600629,
    "priceChange8hPercent": 7.626060693314251,
    "history12hPrice": 4.04550946941609,
    "priceChange12hPercent": 14.201935307925712,
    "history24hPrice": 3.5363177665783287,
    "priceChange24hPercent": 30.645785025389305,
    "uniqueWallet30m": 17,
    "uniqueWalletHistory30m": 14,
    "uniqueWallet30mChangePercent": 21.428571428571427,
    "uniqueWallet1h": 30,
    "uniqueWalletHistory1h": 19,
    "uniqueWallet1hChangePercent": 57.89473684210527,
    "uniqueWallet2h": 44,
    "uniqueWalletHistory2h": 29,
    "uniqueWallet2hChangePercent": 51.724137931034484,
    "uniqueWallet4h": 63,
    "uniqueWalletHistory4h": 79,
    "uniqueWallet4hChangePercent": -20.253164556962027,
    "uniqueWallet8h": 122,
    "uniqueWalletHistory8h": 250,
    "uniqueWallet8hChangePercent": -51.2,
    "uniqueWallet24h": 397,
    "uniqueWalletHistory24h": 430,
    "uniqueWallet24hChangePercent": -7.674418604651163,
    "supply": 2445355.764932173,
    "mc": 11298381.156540288,
    "holder": 19438,
    "trade30m": 29,
    "tradeHistory30m": 28,
    "trade30mChangePercent": 3.571428571428571,
    "sell30m": 16,
    "sellHistory30m": 11,
    "sell30mChangePercent": 45.45454545454545,
    "buy30m": 13,
    "buyHistory30m": 17,
    "buy30mChangePercent": -23.52941176470588,
    "v30m": 810.0436309170184,
    "v30mUSD": 3513.249920976837,
    "vHistory30m": 2822.1856306840314,
    "vHistory30mUSD": 12885.124037210126,
    "v30mChangePercent": -71.29729447595965,
    "vBuy30m": 342.86338709405663,
    "vBuy30mUSD": 1394.638157114759,
    "vBuyHistory30m": 2571.1219650840744,
    "vBuyHistory30mUSD": 11727.90674846191,
    "vBuy30mChangePercent": -86.66483380601335,
    "vSell30m": 467.1802438229618,
    "vSell30mUSD": 2118.611763862078,
    "vSellHistory30m": 251.06366559995683,
    "vSellHistory30mUSD": 1157.2172887482154,
    "vSell30mChangePercent": 86.08038829774902,
    "trade1h": 57,
    "tradeHistory1h": 37,
    "trade1hChangePercent": 54.054054054054056,
    "sell1h": 27,
    "sellHistory1h": 14,
    "sell1hChangePercent": 92.85714285714286,
    "buy1h": 30,
    "buyHistory1h": 23,
    "buy1hChangePercent": 30.434782608695656,
    "v1h": 3632.229261601057,
    "v1hUSD": 15823.101975703788,
    "vHistory1h": 767.9950827370528,
    "vHistory1hUSD": 2799.6446836914147,
    "v1hChangePercent": 372.94954658513933,
    "vBuy1h": 2913.985352178027,
    "vBuy1hUSD": 13120.441296649204,
    "vBuyHistory1h": 488.9871040330243,
    "vBuyHistory1hUSD": 2153.9678326306084,
    "vBuy1hChangePercent": 495.92274073167124,
    "vSell1h": 718.2439094230298,
    "vSell1hUSD": 2702.660679054585,
    "vSellHistory1h": 279.00797870402846,
    "vSellHistory1hUSD": 645.676851060806,
    "vSell1hChangePercent": 157.42773119221175,
    "trade2h": 94,
    "tradeHistory2h": 36,
    "trade2hChangePercent": 161.11111111111111,
    "sell2h": 41,
    "sellHistory2h": 15,
    "sell2hChangePercent": 173.33333333333334,
    "buy2h": 53,
    "buyHistory2h": 21,
    "buy2hChangePercent": 152.38095238095238,
    "v2h": 4400.224344338131,
    "v2hUSD": 19662.34149186454,
    "vHistory2h": 1463.8234275421105,
    "vHistory2hUSD": 6270.304385415777,
    "v2hChangePercent": 200.59802716277733,
    "vBuy2h": 3402.972456211145,
    "vBuy2hUSD": 15164.012617771927,
    "vBuyHistory2h": 850.8346036661075,
    "vBuyHistory2hUSD": 3623.8214452404645,
    "vBuy2hChangePercent": 299.95698829693714,
    "vSell2h": 997.2518881269863,
    "vSell2hUSD": 4498.328874092612,
    "vSellHistory2h": 612.9888238760029,
    "vSellHistory2hUSD": 2646.4829401753127,
    "vSell2hChangePercent": 62.68679774962963,
    "trade4h": 130,
    "tradeHistory4h": 194,
    "trade4hChangePercent": -32.98969072164948,
    "sell4h": 56,
    "sellHistory4h": 95,
    "sell4hChangePercent": -41.05263157894737,
    "buy4h": 74,
    "buyHistory4h": 99,
    "buy4hChangePercent": -25.252525252525253,
    "v4h": 5864.0477718804,
    "v4hUSD": 25776.78917882211,
    "vHistory4h": 6364.844784513337,
    "vHistory4hUSD": 27038.017092099526,
    "v4hChangePercent": -7.868173216909452,
    "vBuy4h": 4253.807059877273,
    "vBuy4hUSD": 19008.627086030487,
    "vBuyHistory4h": 3549.428823439265,
    "vBuyHistory4hUSD": 15388.177600942185,
    "vBuy4hChangePercent": 19.844833393658284,
    "vSell4h": 1610.2407120031273,
    "vSell4hUSD": 6768.162092791623,
    "vSellHistory4h": 2815.4159610740717,
    "vSellHistory4hUSD": 11649.839491157341,
    "vSell4hChangePercent": -42.80629454878753,
    "trade8h": 324,
    "tradeHistory8h": 1258,
    "trade8hChangePercent": -74.24483306836248,
    "sell8h": 151,
    "sellHistory8h": 572,
    "sell8hChangePercent": -73.6013986013986,
    "buy8h": 173,
    "buyHistory8h": 686,
    "buy8hChangePercent": -74.78134110787173,
    "v8h": 12228.892556393275,
    "v8hUSD": 53117.454453597136,
    "vHistory8h": 45294.37690164138,
    "vHistory8hUSD": 176505.19752221502,
    "v8hChangePercent": -73.00130083928778,
    "vBuy8h": 7803.235883315929,
    "vBuy8hUSD": 33989.56367408799,
    "vBuyHistory8h": 27374.404755588977,
    "vBuyHistory8hUSD": 106163.82719365483,
    "vBuy8hChangePercent": -71.49440890866217,
    "vSell8h": 4425.656673077347,
    "vSell8hUSD": 19127.890779509144,
    "vSellHistory8h": 17919.9721460524,
    "vSellHistory8hUSD": 70341.3703285602,
    "vSell8hChangePercent": -75.30321678512053,
    "trade24h": 2131,
    "tradeHistory24h": 2241,
    "trade24hChangePercent": -4.908522980812138,
    "sell24h": 970,
    "sellHistory24h": 1062,
    "sell24hChangePercent": -8.662900188323917,
    "buy24h": 1161,
    "buyHistory24h": 1179,
    "buy24hChangePercent": -1.5267175572519083,
    "v24h": 78630.36919951541,
    "v24hUSD": 300949.3241575769,
    "vHistory24h": 117653.45657416919,
    "vHistory24hUSD": 390469.4827628916,
    "v24hChangePercent": -33.16782057317073,
    "vBuy24h": 43633.27636836614,
    "vBuy24hUSD": 169540.8711670834,
    "vBuyHistory24h": 55772.29907535818,
    "vBuyHistory24hUSD": 185633.97482144056,
    "vBuy24hChangePercent": -21.76532599201279,
    "vSell24h": 34997.09283114926,
    "vSell24hUSD": 131408.4529904935,
    "vSellHistory24h": 61881.157498811015,
    "vSellHistory24hUSD": 204835.50794145107,
    "vSell24hChangePercent": -43.44467000019886,
    "watch": 132,
    "view30m": 13,
    "viewHistory30m": 18,
    "view30mChangePercent": -27.77777777777778,
    "view1h": 28,
    "viewHistory1h": 39,
    "view1hChangePercent": -28.205128205128204,
    "view2h": 67,
    "viewHistory2h": 52,
    "view2hChangePercent": 28.846153846153843,
    "view4h": 119,
    "viewHistory4h": 60,
    "view4hChangePercent": 98.33333333333333,
    "view8h": 179,
    "viewHistory8h": 261,
    "view8hChangePercent": -31.417624521072796,
    "view24h": 597,
    "viewHistory24h": 434,
    "view24hChangePercent": 37.55760368663594,
    "uniqueView30m": 8,
    "uniqueViewHistory30m": 13,
    "uniqueView30mChangePercent": -38.46153846153847,
    "uniqueView1h": 19,
    "uniqueViewHistory1h": 22,
    "uniqueView1hChangePercent": -13.636363636363635,
    "uniqueView2h": 36,
    "uniqueViewHistory2h": 32,
    "uniqueView2hChangePercent": 12.5,
    "uniqueView4h": 60,
    "uniqueViewHistory4h": 38,
    "uniqueView4hChangePercent": 57.89473684210527,
    "uniqueView8h": 85,
    "uniqueViewHistory8h": 109,
    "uniqueView8hChangePercent": -22.018348623853214,
    "uniqueView24h": 229,
    "uniqueViewHistory24h": 180,
    "uniqueView24hChangePercent": 27.22222222222222
  },
  "success": true,
  "statusCode": 200
}
