{
  "data": {
    "address": "PUPS8ZgJ5po4UmNDfqtDMCPP6M1KP3EEzG9Zufcwzrg",
    "decimals": 9,
    "symbol": "PUPS",
    "name": "PUPS",
    "extensions": {
      "coingeckoId": "pups-ordinals",
      "description": "$PUPS, the first meme coin on Bitcoin, and has forever changed the cryptocurrency landscape by conducting the first-ever successful BRC-20 token airdrop on Bitcoin. This milestone is more than a historical feat; it's a testament to $PUPS being 100% free and fair launch. PUPS is just a meme coin. There is zero utility ever. No roadmap. No promises. Only community run memes.",
      "twitter": "https://twitter.com/PupsToken",
      "website": "https://www.pupstoken.com/"
    },
    "logoURI": "https://img.fotofolio.xyz/?w=30\u0026h=30\u0026url=https%3A%2F%2Ftoken-ndllmwrhm.pages.dev%2Fpups%2Ficon.png",
    "numberMarkers": 17,
    "liquidity": 349068.2039875129,
    "lastTradeUnixTime": 1724882753,
    "lastTradeHumanTime": "2024-08-28T22:05:53",
    "price": 4.129762047971172,
    "history30mPrice": 4.171566855327547,
    "priceChange30mPercent": -0.5046760661934544,
    "history1hPrice": 4.130379546682054,
    "priceChange1hPercent": 0.4874711612779024,
    "history2hPrice": 4.33123124338833,
    "priceChange2hPercent": -4.172422976509203,
    "history4hPrice": 4.461695248828451,
    "priceChange4hPercent": -6.974508021064659,
    "history6hPrice": 4.519809592167834,
    "priceChange6hPercent": -8.17060163296081,
    "history8hPrice": 4.559724633664087,
    "priceChange8hPercent": -8.974460317613628,
    "history12hPrice": 4.894896303925491,
    "priceChange12hPercent": -15.207315985531286,
    "history24hPrice": 3.8059368584589977,
    "priceChange24hPercent": 9.05367351532914,
    "uniqueWallet30m": 31,
    "uniqueWalletHistory30m": 25,
    "uniqueWallet30mChangePercent": 24,
    "uniqueWallet1h": 58,
    "uniqueWalletHistory1h": 118,
    "uniqueWallet1hChangePercent": -50.847457627118644,
    "uniqueWallet2h": 137,
    "uniqueWalletHistory2h": 66,
    "uniqueWallet2hChangePercent": 107.57575757575756,
    "uniqueWallet4h": 164,
    "uniqueWalletHistory4h": 153,
    "uniqueWallet4hChangePercent": 7.18954248366013,
    "uniqueWallet8h": 259,
    "uniqueWalletHistory8h": 226,
    "uniqueWallet8hChangePercent": 14.601769911504425,
    "uniqueWallet24h": 462,
    "uniqueWalletHistory24h": 316,
    "uniqueWallet24hChangePercent": 46.20253164556962,
    "supply": 2452526.716722274,
    "mc": 10128351.756354995,
    "holder": 19320,
    "trade30m": 41,
    "tradeHistory30m": 41,
    "trade30mChangePercent": 0,
    "sell30m": 16,
    "sellHistory30m": 21,
    "sell30mChangePercent": -23.809523809523807,
    "buy30m": 25,
    "buyHistory30m": 20,
    "buy30mChangePercent": 25,
    "v30m": 587.2266438100164,
    "v30mUSD": 2283.2729719390236,
    "vHistory30m": 767.0298787240263,
    "vHistory30mUSD": 3167.3922608815965,
    "v30mChangePercent": -23.441490338435983,
    "vBuy30m": 451.08255278605844,
    "vBuy30mUSD": 1737.1748471069418,
    "vBuyHistory30m": 445.56974081407526,
    "vBuyHistory30mUSD": 1853.9808142056445,
    "vBuy30mChangePercent": 1.2372500793952113,
    "vSell30m": 136.1440910239579,
    "vSell30mUSD": 546.098124832082,
    "vSellHistory30m": 321.4601379099511,
    "vSellHistory30mUSD": 1313.4114466759522,
    "vSell30mChangePercent": -57.64821980444268,
    "trade1h": 82,
    "tradeHistory1h": 384,
    "trade1hChangePercent": -78.64583333333334,
    "sell1h": 37,
    "sellHistory1h": 171,
    "sell1hChangePercent": -78.3625730994152,
    "buy1h": 45,
    "buyHistory1h": 213,
    "buy1hChangePercent": -78.87323943661971,
    "v1h": 1354.2565225340486,
    "v1hUSD": 4875.393250337429,
    "vHistory1h": 15284.42459864305,
    "vHistory1hUSD": 62273.66663036858,
    "v1hChangePercent": -91.13963032239842,
    "vBuy1h": 896.6522936000117,
    "vBuy1hUSD": 3589.0520523850873,
    "vBuyHistory1h": 6264.701774981014,
    "vBuyHistory1hUSD": 25765.78479746008,
    "vBuy1hChangePercent": -85.68723099987103,
    "vSell1h": 457.60422893403677,
    "vSell1hUSD": 1286.341197952342,
    "vSellHistory1h": 9019.722823662036,
    "vSellHistory1hUSD": 36507.8818329085,
    "vSell1hChangePercent": -94.92662648420223,
    "trade2h": 466,
    "tradeHistory2h": 157,
    "trade2hChangePercent": 196.81528662420382,
    "sell2h": 208,
    "sellHistory2h": 79,
    "sell2hChangePercent": 163.29113924050634,
    "buy2h": 258,
    "buyHistory2h": 78,
    "buy2hChangePercent": 230.76923076923075,
    "v2h": 16638.681121177142,
    "v2hUSD": 68188.65471317555,
    "vHistory2h": 2902.97679164812,
    "vHistory2hUSD": 12615.451217756194,
    "v2hChangePercent": 473.1592883913753,
    "vBuy2h": 7161.354068581164,
    "vBuy2hUSD": 29244.440338337423,
    "vBuyHistory2h": 861.9463394151213,
    "vBuyHistory2hUSD": 3704.135505071165,
    "vBuy2hChangePercent": 730.8352551784769,
    "vSell2h": 9477.327052595978,
    "vSell2hUSD": 38944.21437483813,
    "vSellHistory2h": 2041.0304522329986,
    "vSellHistory2hUSD": 8911.31571268503,
    "vSell2hChangePercent": 364.3403062520339,
    "trade4h": 623,
    "tradeHistory4h": 619,
    "trade4hChangePercent": 0.6462035541195477,
    "sell4h": 287,
    "sellHistory4h": 293,
    "sell4hChangePercent": -2.04778156996587,
    "buy4h": 336,
    "buyHistory4h": 326,
    "buy4hChangePercent": 3.067484662576687,
    "v4h": 19541.6579128254,
    "v4hUSD": 80648.24923247294,
    "vHistory4h": 22423.582627224358,
    "vHistory4hUSD": 96398.77316224427,
    "v4hChangePercent": -12.852204584382632,
    "vBuy4h": 8023.300407996254,
    "vBuy4hUSD": 33169.36886642651,
    "vBuyHistory4h": 11542.04864265626,
    "vBuyHistory4hUSD": 50298.14050264121,
    "vBuy4hChangePercent": -30.486340368170634,
    "vSell4h": 11518.35750482915,
    "vSell4hUSD": 47478.88036604643,
    "vSellHistory4h": 10881.5339845681,
    "vSellHistory4hUSD": 46100.632659603056,
    "vSell4hChangePercent": 5.852332227829058,
    "trade8h": 1242,
    "tradeHistory8h": 1231,
    "trade8hChangePercent": 0.8935824532900082,
    "sell8h": 580,
    "sellHistory8h": 599,
    "sell8hChangePercent": -3.1719532554257093,
    "buy8h": 662,
    "buyHistory8h": 632,
    "buy8hChangePercent": 4.746835443037975,
    "v8h": 41965.2405400493,
    "v8hUSD": 177349.67057739355,
    "vHistory8h": 51124.341067838424,
    "vHistory8hUSD": 241569.51489782956,
    "v8hChangePercent": -17.915341961348,
    "vBuy8h": 19565.349050651952,
    "vBuy8hUSD": 83060.26835618337,
    "vBuyHistory8h": 25298.946167843005,
    "vBuyHistory8hUSD": 120361.831413947,
    "vBuy8hChangePercent": -22.663383206368163,
    "vSell8h": 22399.891489397352,
    "vSell8hUSD": 94289.40222121018,
    "vSellHistory8h": 25825.394899995423,
    "vSellHistory8hUSD": 121207.68348388257,
    "vSell8hChangePercent": -13.264089179905152,
    "trade24h": 3816,
    "tradeHistory24h": 2394,
    "trade24hChangePercent": 59.3984962406015,
    "sell24h": 1814,
    "sellHistory24h": 906,
    "sell24hChangePercent": 100.22075055187638,
    "buy24h": 2002,
    "buyHistory24h": 1488,
    "buy24hChangePercent": 34.543010752688176,
    "v24h": 151834.00675223788,
    "v24hUSD": 685979.9739184349,
    "vHistory24h": 78766.08785809699,
    "vHistory24hUSD": 342519.2058181799,
    "v24hChangePercent": 92.76570778248912,
    "vBuy24h": 77996.58411829085,
    "vBuy24hUSD": 354318.85232991364,
    "vBuyHistory24h": 37291.95373301109,
    "vBuyHistory24hUSD": 164008.61288572045,
    "vBuy24hChangePercent": 109.1512412481831,
    "vSell24h": 73837.42263394703,
    "vSell24hUSD": 331661.1215885213,
    "vSellHistory24h": 41474.13412508589,
    "vSellHistory24hUSD": 178510.59293245943,
    "vSell24hChangePercent": 78.0324633451142,
    "watch": 122,
    "view30m": 4,
    "viewHistory30m": 1,
    "view30mChangePercent": 300,
    "view1h": 5,
    "viewHistory1h": 16,
    "view1hChangePercent": -68.75,
    "view2h": 21,
    "viewHistory2h": 31,
    "view2hChangePercent": -32.25806451612903,
    "view4h": 52,
    "viewHistory4h": 104,
    "view4hChangePercent": -50,
    "view8h": 156,
    "viewHistory8h": 5577,
    "view8hChangePercent": -97.2027972027972,
    "view24h": 5887,
    "viewHistory24h": 360,
    "view24hChangePercent": 1535.2777777777778,
    "uniqueView30m": 5,
    "uniqueViewHistory30m": 6,
    "uniqueView30mChangePercent": -16.666666666666664,
    "uniqueView1h": 6,
    "uniqueViewHistory1h": 16,
    "uniqueView1hChangePercent": -62.5,
    "uniqueView2h": 21,
    "uniqueViewHistory2h": 23,
    "uniqueView2hChangePercent": -8.695652173913043,
    "uniqueView4h": 41,
    "uniqueViewHistory4h": 68,
    "uniqueView4hChangePercent": -39.705882352941174,
    "uniqueView8h": 96,
    "uniqueViewHistory8h": 91,
    "uniqueView8hChangePercent": 5.4945054945054945,
    "uniqueView24h": 230,
    "uniqueViewHistory24h": 163,
    "uniqueView24hChangePercent": 41.104294478527606
  },
  "success": true,
  "statusCode": 200
}
